winzy_pdf_to_text/__init__.py
winzy_pdf_to_text-0.1.0.dist-info/licenses/LICENSE
winzy_pdf_to_text-0.1.0.dist-info/METADATA
winzy_pdf_to_text-0.1.0.dist-info/WHEEL
winzy_pdf_to_text-0.1.0.dist-info/entry_points.txt
winzy_pdf_to_text-0.1.0.dist-info/top_level.txt
winzy_pdf_to_text-0.1.0.dist-info/RECORD
