Metadata-Version: 2.4
Name: winzy-pdf-to-text
Version: 0.1.0
Summary: Extract text from a given pdf
Author: Sukhbinder Singh
License: Apache-2.0
Project-URL: Homepage, https://github.com/sukhbinder/winzy-pdf-to-text
Project-URL: Changelog, https://github.com/sukhbinder/winzy-pdf-to-text/releases
Project-URL: Issues, https://github.com/sukhbinder/winzy-pdf-to-text/issues
Project-URL: CI, https://github.com/sukhbinder/winzy-pdf-to-text/actions
Classifier: License :: OSI Approved :: Apache Software License
License-File: LICENSE
Requires-Dist: winzy
Requires-Dist: pypdf
Requires-Dist: requests
Provides-Extra: test
Requires-Dist: pytest; extra == "test"
Dynamic: license-file
